{
  "en": {
    "subsystems": "Subsystems",
    "subsystemType": "Subsystem Type",
    "tableName": "Table Name",
    "selectPlaceholder": "Please Select",
    "inputPlaceholder": "Please Input",
    "requiredTableMappings": "Required Table Mappings",
    "optionalTableMappings": "Optional Table Mappings",
    "miscSettings": "Misc Settings",
    "optionalMappings": "Optional Mappings",
    "mappingType": "Mapping Type",
    "columnType": "Column Type",
    "argName": "Argument Name",
    "plugins": "Plugins",
    "pluginType": "Plugin Type",
    "save": "Save",
    "noSubsystem": "No Subsystem",
    "noPlugin": "No Plugin",
    "noOptionalMapping": "No Optional Mapping",
    "saveSuccessfulMessage": "Save Successful",
    "requiredTableMappingsError": "Required table mappings are not complete",
    "optionalTableMappingsError": "Optional table mappings are not complete",
    "miscSettingInvalidError": "Misc settings are not complete",
    "optionalMappingInvalidError": "Optional mappings are not complete"
  },
  "zh": {
    "subsystems": "子系统",
    "subsystemType": "子系统类型",
    "tableName": "表名",
    "selectPlaceholder": "请选择",
    "inputPlaceholder": "请输入",
    "requiredTableMappings": "必需表映射",
    "optionalTableMappings": "可选表映射",
    "miscSettings": "其他设置",
    "optionalMappings": "可选映射",
    "mappingType": "映射类型",
    "columnType": "列类型",
    "argName": "参数名",
    "plugins": "插件",
    "pluginType": "插件类型",
    "save": "保存",
    "noSubsystem": "暂无子系统",
    "noPlugin": "暂无插件",
    "noOptionalMapping": "暂无可选映射",
    "saveSuccessfulMessage": "保存成功",
    "requiredTableMappingsError": "必需表映射未完成",
    "optionalTableMappingsError": "可选表映射未完成",
    "miscSettingInvalidError": "其他设置未完成",
    "optionalMappingInvalidError": "可选映射未完成"
  }
}
