{
  "EN": {
    "title": "Reset Password",
    "email": "Email",
    "phone": "Phone",
    "username": "Username",
    "newPassword": "New Password",
    "confirmPassword": "Confirm Password",
    "emailError": "Please input a valid email address",
    "phoneError": "Please input a valid phone number",
    "usernameError": "Please input your username",
    "newPasswordError": "Please input your new password",
    "confirmPasswordError": "Please confirm your new password",
    "confirmPasswordDifferent": "The two passwords do not match"
  },
  "ZH": {
    "title": "重置密码",
    "email": "邮箱",
    "phone": "手机",
    "username": "用户名",
    "newPassword": "新密码",
    "confirmPassword": "确认密码",
    "emailError": "请输入有效的邮箱地址",
    "phoneError": "请输入有效的手机号码",
    "usernameError": "请输入用户名",
    "newPasswordError": "请输入新密码",
    "confirmPasswordError": "请确认新密码",
    "confirmPasswordDifferent": "两次输入的密码不一致"
  }
}
